{
  "updated": "01 Apr 2026, 09:44 MSK",
  "timestamp": 1775025875,
  "canTrade": true,
  "balances": {
    "USDC.e": 120.82,
    "POL": 102.77
  },
  "balancesUSD": {
    "USDC.e": 120.82,
    "POL": 9.72
  },
  "prices": {
    "BTCUSDT": {
      "price": 69110.99,
      "change": 2.49
    },
    "ETHUSDT": {
      "price": 2152.8,
      "change": 4.55
    },
    "SOLUSDT": {
      "price": 84.61,
      "change": 1.6
    },
    "TONUSDT": {
      "price": 1.23,
      "change": -0.16
    }
  },
  "status": "online",
  "polymarket": {
    "usdc": 120.82,
    "pol": 102.77,
    "polUSD": 9.72,
    "totalUSD": 130.54
  },
  "grandTotalUSD": 339.11,
  "aiTrader": {
    "status": "active",
    "model": "mimo-v2-pro",
    "strategy": "v5 — 3 стратегии (спорт, крипто UP/DOWN, contrarian NO)",
    "cashBalance": 120.82,
    "positionsValue": 208.57,
    "portfolioTotal": 329.39,
    "initialDeposit": 139.74,
    "totalPnL": 189.65,
    "totalPnLpercent": 135.7,
    "activePositions": 15,
    "deadPositions": 7,
    "autoRedeem": true,
    "goal": "$1000",
    "cron": "9 раз/день (06-22 МСК)",
    "stopLoss": "6 раз/день",
    "bot": "@Trader51asic_bot"
  }
}